flask_tenants/__init__.py
flask_tenants/exceptions.py
flask_tenants/middleware.py
flask_tenants/models.py
flask_tenants/utils.py
flask_tenants-0.5.1.dist-info/LICENSE
flask_tenants-0.5.1.dist-info/METADATA
flask_tenants-0.5.1.dist-info/WHEEL
flask_tenants-0.5.1.dist-info/top_level.txt
flask_tenants-0.5.1.dist-info/RECORD
