Metadata-Version: 2.1
Name: flask-tenants
Version: 0.5.1
Summary: A Flask extension for multi-tenancy support
Home-page: https://github.com/Flask-Tenants/flask-tenants
Author: Cory Cline, Gabe Rust
Author-email: support@flasktenants.com
Classifier: Programming Language :: Python :: 3
Classifier: License :: OSI Approved :: MIT License
Classifier: Operating System :: OS Independent
Classifier: Framework :: Flask
Classifier: Development Status :: 4 - Beta
Classifier: Intended Audience :: Developers
Classifier: Topic :: Software Development :: Libraries :: Python Modules
Requires-Python: >=3.6
License-File: LICENSE
Requires-Dist: Flask >=1.1.2
Requires-Dist: SQLAlchemy >=1.3.23
Requires-Dist: psycopg2-binary ==2.9.9
Requires-Dist: Flask-SQLAlchemy ==3.1.1
